clamg/__init__.py
clamg-0.3.1.dist-info/LICENSE
clamg-0.3.1.dist-info/METADATA
clamg-0.3.1.dist-info/WHEEL
clamg-0.3.1.dist-info/top_level.txt
clamg-0.3.1.dist-info/RECORD
