Metadata-Version: 2.1
Name: clamg
Version: 0.3.1
Author-email: Spencer Rak <spencer.rak@gmail.com>
License: MIT
Classifier: Programming Language :: Python :: 3
Requires-Python: >=3
License-File: LICENSE
Requires-Dist: pyyaml
